verilog/cpu.v
/*
RAM: 8 bit address bus
ROM: 16 bit address bus

instruction byte: hhhh llll
    hhhh: OPCODE
    llll: OPERAND

Registers: 
    A: byte
    B: byte
    X: byte
    PC: word
    Out: byte[16]
    In: byte[16]

Conditions: 
    z: A is zero
    m: A is minus (negative)
    c: Carry flag set
    i: Invert all conditions
	  Note 1: Z is least significant bit on operand
		Note 2: If condition is one, that flag must be true to execute instruction. If condition is zero, that flag will ignored
		Note 3: To execute instruction, all considered flags must be true.
		Note 4: Invert bit always invert the result of condition testing. 1000 will always skip instruction and 0000 will always execute instruction
		Note 5: Instructions pha out and inp always execute, ignoring conditions

Instruction set:
0x0 - tab {cond} : Transfer A to B
0x1 - sax {cond} : Swap A and X
0x2 - sta {cond} : Store to A from RAM using B as address
0x3 - lda {cond} : Load to A from RAM using B as address
0x4 - jmp {cond} : Push A and B to PC : A + (B<<8) => PC
0x5 - pha 0bxxxx : Push 4 bit to A
0x6 - out 0bxxxx : Put A to selected Out port
0x7 - inp 0bxxxx : Put selected Out port to A
0x8 - add {cond} : Add B to A
0x9 - sub {cond} : Subtract B from A
0xA - inc {cond} : Increment A
0xB - dec {cond} : Decrement A
0xC - and {cond} : And operation B to A
0xD - ora {cond} : Or operation B to A
0xE - xor {cond} : Xor operation B to A 
0xF - not {cond} : Invert all bits in A
*/

//-----------------------------------------------------------------------------
module cpu(
  input clk, rst,            // Saat ve reset sinyali   
  output [15:0] rom_address, // Program sayacı çıktısı
  input [7:0] rom_data,      // Komut girişi
  output [3:0] io_sel,       // G/Ç port seçimi çıktısı
  output io_reading,         // Girdi okuma sinyali
  output io_output,          // Çıktı yazma sinyali
  inout [7:0] io_data        // G/Ç veri hattı
);
  reg [7:0] RAM[256];
  reg [15:0] program_counter;
  reg [7:0] reg_a;
  reg [7:0] reg_b;
  reg [7:0] reg_x;

  wire [3:0] opcode = rom_data[7:4];
  wire [3:0] operand = rom_data[3:0];
  wire [2:0] condition = operand[2:0];
  wire invert_condition = operand[3];
  wire execute;

  wire [7:0]alu_result;
  wire alu_carry;
  wire alu_carry_set;
  
  reg zero_latch;
  reg minus_latch;
  reg carry_latch;
  
  (* keep *)
  ALU alu_instance (
    .A(reg_a),
    .B(reg_b),
    .operation(opcode[2:0]), 
    .result(alu_result),
    .carry(alu_carry),
    .carry_set(alu_carry_set)
  );

  initial begin // Yazmaçların başlangıç değeri              
    zero_latch = 0;
    minus_latch = 0;
    carry_latch = 0;
    program_counter = 0;
    reg_a = 0;
    reg_b = 0;
    reg_x = 0;
  end

  assign io_sel = (opcode == 4'b0110 || opcode == 4'b0111) ? operand : 4'b0000;
  assign io_output = (opcode == 4'b0110) ? 1'b1 : 1'b0;
  assign io_data = (opcode == 4'b0110) ? reg_a : 8'bzzzzzzzz; // 
  assign io_reading = (opcode == 4'b0111) ? 1'b1 : 1'b0;
  assign rom_address = program_counter;

  wire cond_z = condition[0] ? zero_latch : 1'b1;
  wire cond_m = condition[1] ? minus_latch : 1'b1;
  wire cond_c = condition[2] ? carry_latch : 1'b1;
  wire all_conditions = cond_z & cond_m & cond_c;
  assign execute = invert_condition ? ~all_conditions : all_conditions;

// Program counter update, JMP and INP instruction
  always @ (negedge clk) begin
    //...
    if(execute && opcode == 4'b0100) program_counter <= {reg_b, reg_a};
    else program_counter <= program_counter + 1;
    //...
    if(execute && opcode == 4'b0111) reg_a <= io_data;
  end


  always @ (posedge clk) begin
    if(opcode[3]) begin
      if(execute) begin 
        if(alu_carry_set) carry_latch <= alu_carry;
        zero_latch <= (alu_result == 0) ? 1'b1 : 1'b0;
        minus_latch <= (alu_result[7] == 1'b1) ? 1'b1 : 1'b0;
        reg_a <= alu_result;
      end
    end else begin
      case (opcode[2:0])
        3'b000: if(execute) reg_b <= reg_a; // tab
        3'b001: if(execute) begin // sax
                  reg_a <= reg_x;
                  reg_x <= reg_a;
                end
        3'b010: if(execute) RAM[reg_b] <= reg_a; // sta
        3'b011: if(execute) reg_a <= RAM[reg_b]; // lda
        3'b101: reg_a <= {reg_a[3:0], operand}; // pha
      endcase
    end
  end


// Reset logic
  always @ (*) begin
    if(rst) begin
      zero_latch = 0;
      minus_latch = 0;
      carry_latch = 0;
      reg_a <= 0;
      reg_b <= 0;
      reg_x <= 0;
      program_counter <= 0;
    end
  end


endmodule
//-----------------------------------------------------------------------------
module ALU(
  input [7:0] A,
  input [7:0] B,
  input [2:0] operation,
  output [7:0] result,
  output carry,
  output carry_set 
);
  wire [7:0] op_add_res;
  wire op_add_carry;
  wire [7:0] op_sub_res;
  wire op_sub_carry;
  wire [7:0] op_inc_res;
  wire op_inc_carry;
  wire [7:0] op_dec_res;
  wire op_dec_carry;
  wire [7:0] op_and_res;
  wire [7:0] op_ora_res;
  wire [7:0] op_xor_res;
  wire [7:0] op_not_res;

  assign {op_add_carry, op_add_res} = A + B; // Addition
  assign {op_sub_carry, op_sub_res} = A - B; // Subtraction
  assign {op_inc_carry, op_inc_res} = A + 1; // Increment
  assign {op_dec_carry, op_dec_res} = A - 1; // Decrement
  assign op_and_res = A & B; // And
  assign op_ora_res = A | B; // Or
  assign op_xor_res = A ^ B; // Xor
  assign op_not_res = ~A; // Not

  mux1_8to1 mux_carry_set (
    .in0(1'b1), // Addition
    .in1(1'b1), // Subtraction
    .in2(1'b1), // Increment
    .in3(1'b1), // Decrement
    .in4(1'b0), // And
    .in5(1'b0), // Or
    .in6(1'b0), // Xor
    .in7(1'b0), // Not
    .sel(operation),
    .out(carry_set)
  );

  mux1_8to1 mux_carry(
    .in0(op_add_carry), // Addition
    .in1(op_sub_carry), // Subtraction
    .in2(op_inc_carry), // Increment
    .in3(op_dec_carry), // Decrement
    .in4(1'b0), // And
    .in5(1'b0), // Or
    .in6(1'b0), // Xor
    .in7(1'b0), // Not
    .sel(operation),
    .out(carry)
  );

  mux8_8to1 mux_result(
    .in0(op_add_res), // Addition
    .in1(op_sub_res), // Subtraction
    .in2(op_inc_res), // Increment
    .in3(op_dec_res), // Decrement
    .in4(op_and_res), // And
    .in5(op_ora_res), // Or
    .in6(op_xor_res), // Xor
    .in7(op_not_res), // Not
    .sel(operation),
    .out(result)
  );
  
endmodule

//-----------------------------------------------------------------------------
module mux1_8to1(
  input in0,
  input in1,
  input in2,
  input in3,
  input in4,
  input in5,
  input in6,
  input in7,
  input [2:0] sel,
  output out
);
  assign out = (sel == 3'b000) ? in0 :
               (sel == 3'b001) ? in1 :
               (sel == 3'b010) ? in2 :
               (sel == 3'b011) ? in3 :
               (sel == 3'b100) ? in4 :
               (sel == 3'b101) ? in5 :
               (sel == 3'b110) ? in6 :
               (sel == 3'b111) ? in7 : 1'b0;
endmodule

module mux8_8to1(
  input [7:0] in0,
  input [7:0] in1,
  input [7:0] in2,
  input [7:0] in3,
  input [7:0] in4,
  input [7:0] in5,
  input [7:0] in6,
  input [7:0] in7,
  input [2:0] sel,
  output [7:0] out
);
  assign out = (sel == 3'b000) ? in0 :
               (sel == 3'b001) ? in1 :
               (sel == 3'b010) ? in2 :
               (sel == 3'b011) ? in3 :
               (sel == 3'b100) ? in4 :
               (sel == 3'b101) ? in5 :
               (sel == 3'b110) ? in6 :
               (sel == 3'b111) ? in7 : 8'b00000000;

endmodule

verilog/tester.v
module tester();
  reg clk;
  reg rst;
  wire [15:0] address;
  reg [7:0] mem [0:4128];
  wire [7:0] mem_out = mem[address];
  wire [7:0] cpu_out;
  wire io_output;

  cpu cpu_instance (
    .clk(clk),
    .rst(rst),
    .rom_address(address),
    .rom_data(mem_out),
    .io_sel(),
    .io_data(cpu_out),
    .io_reading(),
    .io_output(io_output)
  );
  initial begin 
    $dumpfile("test.vcd");
    $dumpvars(0, tester);
    $readmemh("out.mem", mem, 0, 494);
  end


  initial begin 
    rst = 0;
    clk = 0;
    #0 rst = 1;
    #4 rst = 0;
    //#10000 $finish;
  end
  always #1 clk = ~clk;
  always @ (posedge clk) begin
    if(address == 16'hFFFF) $finish;
  end
  always @ (posedge io_output) begin
    $display("output: %h", cpu_out);
    // You can add monitoring code here if needed
  end

endmodule

verilog/test.vcd
$date
	Tue Dec 16 20:35:46 2025
$end
$version
	Icarus Verilog
$end
$timescale
	1s
$end
$scope module tester $end
$var wire 8 ! mem_out [7:0] $end
$var wire 1 " io_output $end
$var wire 8 # cpu_out [7:0] $end
$var wire 16 $ address [15:0] $end
$var reg 1 % clk $end
$var reg 1 & rst $end
$scope module cpu_instance $end
$var wire 1 ' all_conditions $end
$var wire 1 % clk $end
$var wire 16 ( rom_address [15:0] $end
$var wire 8 ) rom_data [7:0] $end
$var wire 1 & rst $end
$var wire 4 * operand [3:0] $end
$var wire 4 + opcode [3:0] $end
$var wire 4 , io_sel [3:0] $end
$var wire 1 - io_reading $end
$var wire 1 " io_output $end
$var wire 8 . io_data [7:0] $end
$var wire 1 / invert_condition $end
$var wire 1 0 execute $end
$var wire 3 1 condition [2:0] $end
$var wire 1 2 cond_z $end
$var wire 1 3 cond_m $end
$var wire 1 4 cond_c $end
$var wire 8 5 alu_result [7:0] $end
$var wire 1 6 alu_carry_set $end
$var wire 1 7 alu_carry $end
$var reg 1 8 carry_latch $end
$var reg 1 9 minus_latch $end
$var reg 16 : program_counter [15:0] $end
$var reg 8 ; reg_a [7:0] $end
$var reg 8 < reg_b [7:0] $end
$var reg 8 = reg_x [7:0] $end
$var reg 1 > zero_latch $end
$scope module alu_instance $end
$var wire 8 ? A [7:0] $end
$var wire 8 @ B [7:0] $end
$var wire 8 A op_and_res [7:0] $end
$var wire 8 B op_not_res [7:0] $end
$var wire 8 C op_ora_res [7:0] $end
$var wire 8 D op_xor_res [7:0] $end
$var wire 3 E operation [2:0] $end
$var wire 8 F result [7:0] $end
$var wire 8 G op_sub_res [7:0] $end
$var wire 1 H op_sub_carry $end
$var wire 8 I op_inc_res [7:0] $end
$var wire 1 J op_inc_carry $end
$var wire 8 K op_dec_res [7:0] $end
$var wire 1 L op_dec_carry $end
$var wire 8 M op_add_res [7:0] $end
$var wire 1 N op_add_carry $end
$var wire 1 6 carry_set $end
$var wire 1 7 carry $end
$scope module mux_carry $end
$var wire 1 N in0 $end
$var wire 1 H in1 $end
$var wire 1 J in2 $end
$var wire 1 L in3 $end
$var wire 1 O in4 $end
$var wire 1 P in5 $end
$var wire 1 Q in6 $end
$var wire 1 R in7 $end
$var wire 3 S sel [2:0] $end
$var wire 1 7 out $end
$upscope $end
$scope module mux_carry_set $end
$var wire 1 T in0 $end
$var wire 1 U in1 $end
$var wire 1 V in2 $end
$var wire 1 W in3 $end
$var wire 1 X in4 $end
$var wire 1 Y in5 $end
$var wire 1 Z in6 $end
$var wire 1 [ in7 $end
$var wire 3 \ sel [2:0] $end
$var wire 1 6 out $end
$upscope $end
$scope module mux_result $end
$var wire 8 ] in0 [7:0] $end
$var wire 8 ^ in1 [7:0] $end
$var wire 8 _ in2 [7:0] $end
$var wire 8 ` in3 [7:0] $end
$var wire 8 a in4 [7:0] $end
$var wire 8 b in5 [7:0] $end
$var wire 8 c in6 [7:0] $end
$var wire 8 d in7 [7:0] $end
$var wire 3 e sel [2:0] $end
$var wire 8 f out [7:0] $end
$upscope $end
$upscope $end
$upscope $end
$upscope $end
$enddefinitions $end
$comment Show the parameter values. $end
$dumpall
$end
#0
$dumpvars
b0 f
b101 e
b11111111 d
b0 c
b0 b
b0 a
b11111111 `
b1 _
b0 ^
b0 ]
b101 \
0[
0Z
0Y
0X
1W
1V
1U
1T
b101 S
0R
0Q
0P
0O
0N
b0 M
1L
b11111111 K
0J
b1 I
0H
b0 G
b0 F
b101 E
b0 D
b0 C
b11111111 B
b0 A
b0 @
b0 ?
0>
b0 =
b0 <
b0 ;
b0 :
09
08
07
06
b0 5
14
13
12
b0 1
10
0/
bz .
0-
b0 ,
b101 +
b0 *
b1010000 )
b0 (
1'
1&
0%
b0 $
bz #
0"
b1010000 !
$end
#1
1%
#2
b1 $
b1 (
b1 :
0%
#3
1%
#4
16
b0 E
b0 S
b0 \
b0 e
b0 +
b0 !
b0 )
b10 $
b10 (
b10 :
0%
0&
#5
1%
#6
b1 5
b1 F
b1 f
16
b10 E
b10 S
b10 \
b10 e
b10 +
b100000 !
b100000 )
b11 $
b11 (
b11 :
0%
#7
1%
#8
06
b0 5
b0 F
b0 f
b101 E
b101 S
b101 \
b101 e
b101 +
b1010000 !
b1010000 )
b100 $
b100 (
b100 :
0%
#9
1%
#10
00
0'
02
b1 1
b1 *
b1010001 !
b1010001 )
b101 $
b101 (
b101 :
0%
#11
b1 5
b1 F
b1 f
b1 M
b1 ]
b1 G
b1 ^
b10 I
b10 _
b0 K
b0 `
0L
b1 C
b1 b
b1 D
b1 c
b11111110 B
b11111110 d
b1 ;
b1 ?
1%
#12
10
1'
12
16
b0 E
b0 S
b0 \
b0 e
b0 1
b0 +
b0 *
b0 !
b0 )
b110 $
b110 (
b110 :
0%
#13
b10 5
b10 F
b10 f
b10 M
b10 ]
b0 G
b0 ^
b1 A
b1 a
b0 D
b0 c
b1 <
b1 @
1%
#14
06
b1 5
b1 F
b1 f
b101 E
b101 S
b101 \
b101 e
b101 +
b1010000 !
b1010000 )
b111 $
b111 (
b111 :
0%
#15
b10001 5
b10001 F
b10001 f
b10001 M
b10001 ]
b1111 G
b1111 ^
b10001 I
b10001 _
b1111 K
b1111 `
b0 A
b0 a
b10001 C
b10001 b
b10001 D
b10001 c
b11101111 B
b11101111 d
b10000 ;
b10000 ?
1%
#16
00
0'
02
b1 1
b1 *
b1010001 !
b1010001 )
b1000 $
b1000 (
b1000 :
0%
#17
b1 5
b1 F
b1 f
b10 M
b10 ]
b0 G
b0 ^
b10 I
b10 _
b0 K
b0 `
b1 A
b1 a
b1 C
b1 b
b0 D
b0 c
b11111110 B
b11111110 d
b1 ;
b1 ?
1%
#18
10
1'
16
b10 5
b10 F
b10 f
12
b10 E
b10 S
b10 \
b10 e
b0 1
b10 +
b0 *
b100000 !
b100000 )
b1001 $
b1001 (
b1001 :
0%
#19
1%
#20
06
b1 5
b1 F
b1 f
b101 E
b101 S
b101 \
b101 e
b101 +
b1010000 !
b1010000 )
b1010 $
b1010 (
b1010 :
0%
#21
b10001 5
b10001 F
b10001 f
b10001 M
b10001 ]
b1111 G
b1111 ^
b10001 I
b10001 _
b1111 K
b1111 `
b0 A
b0 a
b10001 C
b10001 b
b10001 D
b10001 c
b11101111 B
b11101111 d
b10000 ;
b10000 ?
1%
#22
00
0'
03
b10 1
b10 *
b1010010 !
b1010010 )
b1011 $
b1011 (
b1011 :
0%
#23
b11 5
b11 F
b11 f
b11 M
b11 ]
b1 G
b1 ^
b11 I
b11 _
b1 K
b1 `
b11 C
b11 b
b11 D
b11 c
b11111101 B
b11111101 d
b10 ;
b10 ?
1%
#24
10
1'
13
16
b0 E
b0 S
b0 \
b0 e
b0 1
b0 +
b0 *
b0 !
b0 )
b1100 $
b1100 (
b1100 :
0%
#25
b100 5
b100 F
b100 f
b100 M
b100 ]
b0 G
b0 ^
b10 A
b10 a
b10 C
b10 b
b0 D
b0 c
b10 <
b10 @
1%
#26
06
b10 5
b10 F
b10 f
b101 E
b101 S
b101 \
b101 e
b101 +
b1010000 !
b1010000 )
b1101 $
b1101 (
b1101 :
0%
#27
b100010 5
b100010 F
b100010 f
b100010 M
b100010 ]
b11110 G
b11110 ^
b100001 I
b100001 _
b11111 K
b11111 `
b0 A
b0 a
b100010 C
b100010 b
b100010 D
b100010 c
b11011111 B
b11011111 d
b100000 ;
b100000 ?
1%
#28
b1110 $
b1110 (
b1110 :
0%
#29
b10 5
b10 F
b10 f
b10 M
b10 ]
b11111110 G
b11111110 ^
1H
b1 I
b1 _
b11111111 K
b11111111 `
1L
b10 C
b10 b
b10 D
b10 c
b11111111 B
b11111111 d
b0 ;
b0 ?
1%
#30
16
b1 5
b1 F
b1 f
b10 E
b10 S
b10 \
b10 e
b10 +
b100000 !
b100000 )
b1111 $
b1111 (
b1111 :
0%
#31
1%
#32
06
b10 5
b10 F
b10 f
b101 E
b101 S
b101 \
b101 e
b101 +
b1010000 !
b1010000 )
b10000 $
b10000 (
b10000 :
0%
#33
1%
#34
00
0'
02
03
b11 1
b11 *
b1010011 !
b1010011 )
b10001 $
b10001 (
b10001 :
0%
#35
b11 5
b11 F
b11 f
b101 M
b101 ]
b1 G
b1 ^
0H
b100 I
b100 _
b10 K
b10 `
0L
b10 A
b10 a
b11 C
b11 b
b1 D
b1 c
b11111100 B
b11111100 d
b11 ;
b11 ?
1%
#36
10
1'
12
13
16
b101 5
b101 F
b101 f
b0 E
b0 S
b0 \
b0 e
b0 1
b0 +
b0 *
b0 !
b0 )
b10010 $
b10010 (
b10010 :
0%
#37
b110 5
b110 F
b110 f
b110 M
b110 ]
b0 G
b0 ^
b11 A
b11 a
b0 D
b0 c
b11 <
b11 @
1%
#38
06
b11 5
b11 F
b11 f
b101 E
b101 S
b101 \
b101 e
b101 +
b1010000 !
b1010000 )
b10011 $
b10011 (
b10011 :
0%
#39
b110011 5
b110011 F
b110011 f
b110011 M
b110011 ]
b101101 G
b101101 ^
b110001 I
b110001 _
b101111 K
b101111 `
b0 A
b0 a
b110011 C
b110011 b
b110011 D
b110011 c
b11001111 B
b11001111 d
b110000 ;
b110000 ?
1%
#40
b10100 $
b10100 (
b10100 :
0%
#41
b11 5
b11 F
b11 f
b11 M
b11 ]
b11111101 G
b11111101 ^
1H
b1 I
b1 _
b11111111 K
b11111111 `
1L
b11 C
b11 b
b11 D
b11 c
b11111111 B
b11111111 d
b0 ;
b0 ?
1%
#42
16
b1 5
b1 F
b1 f
b10 E
b10 S
b10 \
b10 e
b10 +
b100000 !
b100000 )
b10101 $
b10101 (
b10101 :
0%
#43
1%
#44
06
b11 5
b11 F
b11 f
b101 E
b101 S
b101 \
b101 e
b101 +
b1010000 !
b1010000 )
b10110 $
b10110 (
b10110 :
0%
#45
1%
#46
b10111 $
b10111 (
b10111 :
0%
#47
1%
#48
16
b0 E
b0 S
b0 \
b0 e
b0 +
b0 !
b0 )
b11000 $
b11000 (
b11000 :
0%
#49
b0 5
b0 F
b0 f
b0 M
b0 ]
b0 G
b0 ^
0H
b0 C
b0 b
b0 D
b0 c
b0 <
b0 @
1%
#50
17
b11111111 5
b11111111 F
b11111111 f
16
b11 E
b11 S
b11 \
b11 e
b11 +
b110000 !
b110000 )
b11001 $
b11001 (
b11001 :
0%
#51
1%
#52
07
b0 5
b0 F
b0 f
b1 E
b1 S
b1 \
b1 e
b1 +
b10000 !
b10000 )
b11010 $
b11010 (
b11010 :
0%
#53
1%
#54
06
b101 E
b101 S
b101 \
b101 e
b101 +
b1010000 !
b1010000 )
b11011 $
b11011 (
b11011 :
0%
#55
1%
#56
00
0'
02
b1 1
b1 *
b1010001 !
b1010001 )
b11100 $
b11100 (
b11100 :
0%
#57
b1 5
b1 F
b1 f
b1 M
b1 ]
b1 G
b1 ^
b10 I
b10 _
b0 K
b0 `
0L
b1 C
b1 b
b1 D
b1 c
b11111110 B
b11111110 d
b1 ;
b1 ?
1%
#58
10
1'
12
16
b0 E
b0 S
b0 \
b0 e
b0 1
b0 +
b0 *
b0 !
b0 )
b11101 $
b11101 (
b11101 :
0%
#59
b10 5
b10 F
b10 f
b10 M
b10 ]
b0 G
b0 ^
b1 A
b1 a
b0 D
b0 c
b1 <
b1 @
1%
#60
16
b0 5
b0 F
b0 f
b11 E
b11 S
b11 \
b11 e
b11 +
b110000 !
b110000 )
b11110 $
b11110 (
b11110 :
0%
#61
1%
#62
b10 5
b10 F
b10 f
b0 E
b0 S
b0 \
b0 e
b0 +
b0 !
b0 )
b11111 $
b11111 (
b11111 :
0%
#63
1%
#64
b0 5
b0 F
b0 f
b1 E
b1 S
b1 \
b1 e
b1 +
b10000 !
b10000 )
b100000 $
b100000 (
b100000 :
0%
#65
b11111111 5
b11111111 F
b11111111 f
17
b1 M
b1 ]
b11111111 G
b11111111 ^
1H
b1 I
b1 _
b11111111 K
b11111111 `
1L
b0 A
b0 a
b1 D
b1 c
b11111111 B
b11111111 d
b1 =
b0 ;
b0 ?
1%
#66
07
b1 5
b1 F
b1 f
b0 E
b0 S
b0 \
b0 e
b1000 +
b10000000 !
b10000000 )
b100001 $
b100001 (
b100001 :
0%
#67
b10 5
b10 F
b10 f
b10 M
b10 ]
b0 G
b0 ^
0H
b10 I
b10 _
b0 K
b0 `
0L
b1 A
b1 a
b0 D
b0 c
b11111110 B
b11111110 d
b1 ;
b1 ?
1%
#68
b0 5
b0 F
b0 f
b1 E
b1 S
b1 \
b1 e
b1 +
b10000 !
b10000 )
b100010 $
b100010 (
b100010 :
0%
#69
1%
#70
b1 5
b1 F
b1 f
06
b101 E
b101 S
b101 \
b101 e
b101 +
b1010000 !
b1010000 )
b100011 $
b100011 (
b100011 :
0%
#71
b10001 5
b10001 F
b10001 f
b10001 M
b10001 ]
b1111 G
b1111 ^
b10001 I
b10001 _
b1111 K
b1111 `
b0 A
b0 a
b10001 C
b10001 b
b10001 D
b10001 c
b11101111 B
b11101111 d
b10000 ;
b10000 ?
1%
#72
00
0'
03
b10 1
b10 *
b1010010 !
b1010010 )
b100100 $
b100100 (
b100100 :
0%
#73
b11 5
b11 F
b11 f
b11 M
b11 ]
b1 G
b1 ^
b11 I
b11 _
b1 K
b1 `
b11 C
b11 b
b11 D
b11 c
b11111101 B
b11111101 d
b10 ;
b10 ?
1%
#74
10
1'
13
16
b0 E
b0 S
b0 \
b0 e
b0 1
b0 +
b0 *
b0 !
b0 )
b100101 $
b100101 (
b100101 :
0%
#75
b100 5
b100 F
b100 f
b100 M
b100 ]
b0 G
b0 ^
b10 A
b10 a
b10 C
b10 b
b0 D
b0 c
b10 <
b10 @
1%
#76
b0 5
b0 F
b0 f
b1 E
b1 S
b1 \
b1 e
b1 +
b10000 !
b10000 )
b100110 $
b100110 (
b100110 :
0%
#77
b11111111 5
b11111111 F
b11111111 f
17
b11 M
b11 ]
b11111111 G
b11111111 ^
1H
b10 I
b10 _
b0 K
b0 `
b0 A
b0 a
b11 C
b11 b
b11 D
b11 c
b11111110 B
b11111110 d
b10 =
b1 ;
b1 ?
1%
#78
07
b10 5
b10 F
b10 f
b10 E
b10 S
b10 \
b10 e
b10 +
b100000 !
b100000 )
b100111 $
b100111 (
b100111 :
0%
#79
1%
#80
06
b11 5
b11 F
b11 f
b101 E
b101 S
b101 \
b101 e
b101 +
b1010000 !
b1010000 )
b101000 $
b101000 (
b101000 :
0%
#81
b10010 5
b10010 F
b10010 f
b10010 M
b10010 ]
b1110 G
b1110 ^
0H
b10001 I
b10001 _
b1111 K
b1111 `
b10010 C
b10010 b
b10010 D
b10010 c
b11101111 B
b11101111 d
b10000 ;
b10000 ?
1%
#82
00
0'
02
b1 1
b1 *
b1010001 !
b1010001 )
b101001 $
b101001 (
b101001 :
0%
#83
b11 5
b11 F
b11 f
b11 M
b11 ]
b11111111 G
b11111111 ^
1H
b10 I
b10 _
b0 K
b0 `
b11 C
b11 b
b11 D
b11 c
b11111110 B
b11111110 d
b1 ;
b1 ?
1%
#84
10
1'
12
16
b0 E
b0 S
b0 \
b0 e
b0 1
b0 +
b0 *
b0 !
b0 )
b101010 $
b101010 (
b101010 :
0%
#85
b10 5
b10 F
b10 f
b10 M
b10 ]
b0 G
b0 ^
0H
b1 A
b1 a
b1 C
b1 b
b0 D
b0 c
b1 <
b1 @
1%
#86
16
b0 5
b0 F
b0 f
b11 E
b11 S
b11 \
b11 e
b11 +
b110000 !
b110000 )
b101011 $
b101011 (
b101011 :
0%
#87
1%
#88
b1 E
b1 S
b1 \
b1 e
b1 +
b10000 !
b10000 )
b101100 $
b101100 (
b101100 :
0%
#89
b1 5
b1 F
b1 f
b11 M
b11 ]
b1 G
b1 ^
b11 I
b11 _
b1 K
b1 `
b0 A
b0 a
b11 C
b11 b
b11 D
b11 c
b11111101 B
b11111101 d
b1 =
b10 ;
b10 ?
1%
#90
06
b11 5
b11 F
b11 f
b101 E
b101 S
b101 \
b101 e
b101 +
b1010000 !
b1010000 )
b101101 $
b101101 (
b101101 :
0%
#91
b100001 5
b100001 F
b100001 f
b100001 M
b100001 ]
b11111 G
b11111 ^
b100001 I
b100001 _
b11111 K
b11111 `
b100001 C
b100001 b
b100001 D
b100001 c
b11011111 B
b11011111 d
b100000 ;
b100000 ?
1%
#92
b101110 $
b101110 (
b101110 :
0%
#93
b1 5
b1 F
b1 f
b1 M
b1 ]
b11111111 G
b11111111 ^
1H
b1 I
b1 _
b11111111 K
b11111111 `
1L
b1 C
b1 b
b1 D
b1 c
b11111111 B
b11111111 d
b0 ;
b0 ?
1%
#94
16
b0 E
b0 S
b0 \
b0 e
b0 +
b0 !
b0 )
b101111 $
b101111 (
b101111 :
0%
#95
b0 5
b0 F
b0 f
b0 M
b0 ]
b0 G
b0 ^
0H
b0 C
b0 b
b0 D
b0 c
b0 <
b0 @
1%
#96
b1 E
b1 S
b1 \
b1 e
b1 +
b10000 !
b10000 )
b110000 $
b110000 (
b110000 :
0%
#97
b1 5
b1 F
b1 f
b1 M
b1 ]
b1 G
b1 ^
b10 I
b10 _
b0 K
b0 `
0L
b1 C
b1 b
b1 D
b1 c
b11111110 B
b11111110 d
b0 =
b1 ;
b1 ?
1%
#98
b10 5
b10 F
b10 f
b10 E
b10 S
b10 \
b10 e
b10 +
b100000 !
b100000 )
b110001 $
b110001 (
b110001 :
0%
#99
1%
#100
06
b1 5
b1 F
b1 f
b101 E
b101 S
b101 \
b101 e
b101 +
b1010000 !
b1010000 )
b110010 $
b110010 (
b110010 :
0%
#101
b10000 5
b10000 F
b10000 f
b10000 M
b10000 ]
b10000 G
b10000 ^
b10001 I
b10001 _
b1111 K
b1111 `
b10000 C
b10000 b
b10000 D
b10000 c
b11101111 B
b11101111 d
b10000 ;
b10000 ?
1%
#102
00
0'
03
b10 1
b10 *
b1010010 !
b1010010 )
b110011 $
b110011 (
b110011 :
0%
#103
b10 5
b10 F
b10 f
b10 M
b10 ]
b10 G
b10 ^
b11 I
b11 _
b1 K
b1 `
b10 C
b10 b
b10 D
b10 c
b11111101 B
b11111101 d
b10 ;
b10 ?
1%
#104
10
1'
13
16
b0 E
b0 S
b0 \
b0 e
b0 1
b0 +
b0 *
b0 !
b0 )
b110100 $
b110100 (
b110100 :
0%
#105
b100 5
b100 F
b100 f
b100 M
b100 ]
b0 G
b0 ^
b10 A
b10 a
b0 D
b0 c
b10 <
b10 @
1%
#106
16
b1 5
b1 F
b1 f
b11 E
b11 S
b11 \
b11 e
b11 +
b110000 !
b110000 )
b110101 $
b110101 (
b110101 :
0%
#107
b0 5
b0 F
b0 f
b11 M
b11 ]
b11111111 G
b11111111 ^
1H
b10 I
b10 _
b0 K
b0 `
b0 A
b0 a
b11 C
b11 b
b11 D
b11 c
b11111110 B
b11111110 d
b1 ;
b1 ?
1%
#108
17
b11111111 5
b11111111 F
b11111111 f
b1 E
b1 S
b1 \
b1 e
b1 +
b10000 !
b10000 )
b110110 $
b110110 (
b110110 :
0%
#109
b11111110 5
b11111110 F
b11111110 f
b10 M
b10 ]
b11111110 G
b11111110 ^
b1 I
b1 _
b11111111 K
b11111111 `
1L
b10 C
b10 b
b10 D
b10 c
b11111111 B
b11111111 d
b1 =
b0 ;
b0 ?
1%
#110
07
06
b10 5
b10 F
b10 f
b101 E
b101 S
b101 \
b101 e
b101 +
b1010000 !
b1010000 )
b110111 $
b110111 (
b110111 :
0%
#111
1%
#112
00
0'
02
b1 1
b1 *
b1010001 !
b1010001 )
b111000 $
b111000 (
b111000 :
0%
#113
b11 5
b11 F
b11 f
b11 M
b11 ]
b11111111 G
b11111111 ^
b10 I
b10 _
b0 K
b0 `
0L
b11 C
b11 b
b11 D
b11 c
b11111110 B
b11111110 d
b1 ;
b1 ?
1%
#114
10
1'
12
16
b0 E
b0 S
b0 \
b0 e
b0 1
b0 +
b0 *
b0 !
b0 )
b111001 $
b111001 (
b111001 :
0%
#115
b10 5
b10 F
b10 f
b10 M
b10 ]
b0 G
b0 ^
0H
b1 A
b1 a
b1 C
b1 b
b0 D
b0 c
b1 <
b1 @
1%
#116
b0 5
b0 F
b0 f
b1 E
b1 S
b1 \
b1 e
b1 +
b10000 !
b10000 )
b111010 $
b111010 (
b111010 :
0%
#117
1%
#118
b10 5
b10 F
b10 f
b10 E
b10 S
b10 \
b10 e
b10 +
b100000 !
b100000 )
b111011 $
b111011 (
b111011 :
0%
#119
1%
#120
06
b1 5
b1 F
b1 f
b101 E
b101 S
b101 \
b101 e
b101 +
b1010000 !
b1010000 )
b111100 $
b111100 (
b111100 :
0%
#121
b10001 5
b10001 F
b10001 f
b10001 M
b10001 ]
b1111 G
b1111 ^
b10001 I
b10001 _
b1111 K
b1111 `
b0 A
b0 a
b10001 C
b10001 b
b10001 D
b10001 c
b11101111 B
b11101111 d
b10000 ;
b10000 ?
1%
#122
b111101 $
b111101 (
b111101 :
0%
#123
b1 5
b1 F
b1 f
b1 M
b1 ]
b11111111 G
b11111111 ^
1H
b1 I
b1 _
b11111111 K
b11111111 `
1L
b1 C
b1 b
b1 D
b1 c
b11111111 B
b11111111 d
b0 ;
b0 ?
1%
#124
16
b0 E
b0 S
b0 \
b0 e
b0 +
b0 !
b0 )
b111110 $
b111110 (
b111110 :
0%
#125
b0 5
b0 F
b0 f
b0 M
b0 ]
b0 G
b0 ^
0H
b0 C
b0 b
b0 D
b0 c
b0 <
b0 @
1%
#126
00
0'
03
04
06
b101 E
b101 S
b101 \
b101 e
b110 1
b101 +
b110 *
b1010110 !
b1010110 )
b111111 $
b111111 (
b111111 :
0%
